chameleongram/__init__.py
chameleongram/auth_key.py
chameleongram/client.py
chameleongram/crypto.py
chameleongram/filters.py
chameleongram/utils.py
chameleongram/connection/__init__.py
chameleongram/connection/connection.py
chameleongram/connection/transports.py
chameleongram/exceptions/__init__.py
chameleongram/exceptions/already_started.py
chameleongram/exceptions/invalid_token.py
chameleongram/exceptions/needed_sign_up.py
chameleongram/exceptions/now_stop.py
chameleongram/exceptions/phone_number_invalid.py
chameleongram/exceptions/propagate.py
chameleongram/exceptions/rpc_error.py
chameleongram/handlers/__init__.py
chameleongram/handlers/basic_handler.py
chameleongram/handlers/raw_handler.py
chameleongram/handlers/update_handler.py
chameleongram/methods/__init__.py
chameleongram/methods/base.py
chameleongram/methods/profile/__init__.py
chameleongram/methods/profile/get_me.py
chameleongram/methods/utils/__init__.py
chameleongram/methods/utils/connect.py
chameleongram/methods/utils/run.py
chameleongram/methods/utils/sign_in.py
chameleongram/methods/utils/sign_up.py
chameleongram/methods/utils/start.py
chameleongram/methods/utils/stop.py
chameleongram/raw/__init__.py
chameleongram/raw/_all.py
chameleongram/raw/primitives.py
chameleongram/raw/reader.py
chameleongram/raw/tl_base.py
chameleongram/raw/core/__init__.py
chameleongram/raw/core/functions/__init__.py
chameleongram/raw/core/types/__init__.py
chameleongram/raw/core/types/help.py
chameleongram/raw/functions/__init__.py
chameleongram/raw/functions/account.py
chameleongram/raw/functions/auth.py
chameleongram/raw/functions/bots.py
chameleongram/raw/functions/channels.py
chameleongram/raw/functions/contacts.py
chameleongram/raw/functions/folders.py
chameleongram/raw/functions/help.py
chameleongram/raw/functions/langpack.py
chameleongram/raw/functions/messages.py
chameleongram/raw/functions/payments.py
chameleongram/raw/functions/phone.py
chameleongram/raw/functions/photos.py
chameleongram/raw/functions/stats.py
chameleongram-0.0.2.dist-info/LICENSE
chameleongram-0.0.2.dist-info/METADATA
chameleongram-0.0.2.dist-info/WHEEL
chameleongram-0.0.2.dist-info/top_level.txt
chameleongram-0.0.2.dist-info/RECORD
